odoo/addons/shipment_advice_bill_auto_complete_mrp/README.rst
odoo/addons/shipment_advice_bill_auto_complete_mrp/__init__.py
odoo/addons/shipment_advice_bill_auto_complete_mrp/__manifest__.py
odoo/addons/shipment_advice_bill_auto_complete_mrp/i18n/shipment_advice_bill_auto_complete_mrp.pot
odoo/addons/shipment_advice_bill_auto_complete_mrp/models/__init__.py
odoo/addons/shipment_advice_bill_auto_complete_mrp/models/account_move.py
odoo/addons/shipment_advice_bill_auto_complete_mrp/readme/CONTRIBUTORS.rst
odoo/addons/shipment_advice_bill_auto_complete_mrp/readme/DESCRIPTION.rst
odoo/addons/shipment_advice_bill_auto_complete_mrp/static/description/icon.png
odoo/addons/shipment_advice_bill_auto_complete_mrp/static/description/index.html
odoo/addons/shipment_advice_bill_auto_complete_mrp/tests/__init__.py
odoo/addons/shipment_advice_bill_auto_complete_mrp/tests/test_shipment_advice_bill_auto_complete_mrp.py
odoo14_addon_shipment_advice_bill_auto_complete_mrp-14.0.1.1.0.dist-info/METADATA
odoo14_addon_shipment_advice_bill_auto_complete_mrp-14.0.1.1.0.dist-info/WHEEL
odoo14_addon_shipment_advice_bill_auto_complete_mrp-14.0.1.1.0.dist-info/top_level.txt
odoo14_addon_shipment_advice_bill_auto_complete_mrp-14.0.1.1.0.dist-info/RECORD
