Metadata-Version: 2.1
Name: odoo14-addon-shipment_advice_bill_auto_complete_mrp
Version: 14.0.1.1.0
Summary: Glue module between Shipment Advice Bill Auto Complete and MRP
Home-page: https://github.com/OCA/stock-logistics-transport
Author: Camptocamp, Odoo Community Association (OCA)
Author-email: support@odoo-community.org
License: AGPL-3
Classifier: Programming Language :: Python
Classifier: Framework :: Odoo
Classifier: Framework :: Odoo :: 14.0
Classifier: License :: OSI Approved :: GNU Affero General Public License v3
Classifier: Development Status :: 3 - Alpha
Requires-Python: >=3.6
Requires-Dist: odoo14-addon-shipment-advice-bill-auto-complete
Requires-Dist: odoo <14.1dev,>=14.0a
